Vinit_STT/__init__.py
Vinit_STT-0.1.dist-info/METADATA
Vinit_STT-0.1.dist-info/WHEEL
Vinit_STT-0.1.dist-info/top_level.txt
Vinit_STT-0.1.dist-info/RECORD
