Metadata-Version: 2.1
Name: Vinit-STT
Version: 0.1
Summary: This is a speech to text package created by Vinit Kumar Jha
Author: Vinit Kumar Jha
Author-email: vinitjha2712@gmail.com
